nbtopy.py
nbtopy-1.3.dist-info/METADATA
nbtopy-1.3.dist-info/WHEEL
nbtopy-1.3.dist-info/entry_points.txt
nbtopy-1.3.dist-info/top_level.txt
nbtopy-1.3.dist-info/RECORD
