Metadata-Version: 2.4
Name: nbtopy
Version: 1.3
Summary: Converts Jupyter notebook files to Python (interactive) files
Author-email: Mark Blakeney <mark.blakeney@bullet-systems.net>
License-Expression: GPL-3.0-or-later
Project-URL: Homepage, https://github.com/bulletmark/nbtopy
Keywords: jupyter,notebook,nbconvert,vscode
Classifier: Programming Language :: Python :: 3
Requires-Python: >=3.8
Requires-Dist: argparse-from-file
Requires-Dist: importlib-metadata; python_version < "3.8"
